disco_cli.py
cli/__init__.py
cli/auth_commands.py
cli/cluster_commands.py
cli/command_utils.py
cli/common_options.py
cli/config_commands.py
cli/context_state.py
cli/docker_image_commands.py
cli/job_commands.py
cli/repository_commands.py
cli/task_commands.py
cli/version_commands.py
cli/utilities/__init__.py
cli/utilities/utils.py
disco/__init__.py
disco/asset.py
disco/base_controller.py
disco/cluster.py
disco/docker_image.py
disco/job.py
disco/repository.py
disco/task.py
disco/core/__init__.py
disco/core/config.py
disco/core/constants.py
disco/core/credentials.py
disco/core/exception_factory.py
disco/core/exceptions.py
disco/core/progress_bar.py
disco/core/utils.py
disco/core/zip_tools.py
disco/gql/__init__.py
disco/gql/authentication.py
disco/gql/query.py
disco/gql/request_mixin.py
disco/gql/commands/__init__.py
disco/gql/commands/archiveJob.gql
disco/gql/commands/createJob.gql
disco/gql/commands/fetchCurrentUser.gql
disco/gql/commands/fetchJob.gql
disco/gql/commands/fetchJobStatus.gql
disco/gql/commands/fetchProfileClusters.gql
disco/gql/commands/fetchTaskAuditEvents.gql
disco/gql/commands/findJobsByProfile.gql
disco/gql/commands/findTasksByJob.gql
disco/gql/commands/getArtifactsRepositories.gql
disco/gql/commands/getDockerImagesByOwnerId.gql
disco/gql/commands/login.gql
disco/gql/commands/startJob.gql
disco/gql/commands/stopJob.gql
disco/models/__init__.py
disco/models/base_model.py
disco/models/cluster_details.py
disco/models/docker_image_details.py
disco/models/job_details.py
disco/models/repository_details.py
disco/models/task.py
disco/models/task_audit_event_details.py
discomp/__init__.py
discomp/analytics.py
discomp/job_file_handler.py
discomp/job_handler.py
discomp/pool.py
discomp/process.py
discomp/requirements.txt
discomp/setup.py
discomp/utils.py
discomp/tests/__init__.py
discomp/tests/func_examples.py
discomp/tests/test_pool.py
discomp/tests/test_process.py
discomp/tests/live/__init__.py
discomp/tests/live/test_live_discomp.py
disco-1.40.4.dist-info/LICENSE.txt
disco-1.40.4.dist-info/METADATA
disco-1.40.4.dist-info/WHEEL
disco-1.40.4.dist-info/entry_points.txt
disco-1.40.4.dist-info/top_level.txt
disco-1.40.4.dist-info/RECORD
