Metadata-Version: 2.1
Name: disco
Version: 1.40.4
Summary: Run Python jobs on the cloud using DISCO
Home-page: https://github.com/Iqoqo/python-sdk
Author: Disco
Author-email: contact@dis.co
License: UNKNOWN
Platform: UNKNOWN
Classifier: Programming Language :: Python :: 3.6
Classifier: Programming Language :: Python :: 3.7
Classifier: Programming Language :: Python :: 3.8
Classifier: Operating System :: OS Independent
Requires-Python: >=3.6
Requires-Dist: requests (~=2.22)
Requires-Dist: urllib3 (~=1.25)
Requires-Dist: setuptools
Requires-Dist: click (==7.0)
Requires-Dist: tabulate (==0.8.6)
Requires-Dist: packaging (==19.2)
Requires-Dist: requests-toolbelt (==0.9.1)
Requires-Dist: tqdm (==4.41.0)
Requires-Dist: azure-storage-blob (==12.1.0)
Requires-Dist: bson (==0.5.9)
Requires-Dist: moment (==0.8.2)
